{"schema":{"fields":[{"name":"name","type":"string"},{"name":"value","type":"integer"}],"pandas_version":"0.20.0"},"data":[{"name":"Actualités","value":33010242},{"name":"Politique","value":1435331},{"name":"Economie","value":1336640},{"name":"Religion","value":1281123},{"name":"Alimentation","value":39687},{"name":"Actualités locales","value":25249689},{"name":"Sciences","value":301162},{"name":"Technologies","value":28193},{"name":"Urbanisme","value":44421},{"name":"Sports","value":1273283},{"name":"Satire","value":327357},{"name":"Actualités étrangères","value":594146},{"name":"Environnement","value":48424},{"name":"Ecologie","value":57714},{"name":"Médecine","value":385141},{"name":"Agriculture","value":403038},{"name":"Actualités littéraires","value":8000},{"name":"Reportages","value":26310},{"name":"Enquêtes sociales","value":18511},{"name":"Société","value":367505},{"name":"Enquêtes","value":40098},{"name":"Fonction publique territoriale","value":307140},{"name":"Initiatives citoyennes","value":42252},{"name":"Art","value":63529},{"name":"Transports","value":50000},{"name":"Culture","value":40000},{"name":"Philosophie","value":100314},{"name":"Cinéma","value":129569},{"name":"Artisanat","value":5658},{"name":"Droit","value":393755},{"name":"Comptabilité","value":78751},{"name":"Management","value":78751},{"name":"Santé","value":38088},{"name":"Photo","value":30000},{"name":"Récit","value":35463},{"name":"Littérature","value":3518}]}